skautils/__init__.py
skautils/exehelper.py
skautils-0.0.4.dist-info/LICENSE
skautils-0.0.4.dist-info/METADATA
skautils-0.0.4.dist-info/WHEEL
skautils-0.0.4.dist-info/top_level.txt
skautils-0.0.4.dist-info/RECORD
