Metadata-Version: 2.1
Name: skautils
Version: 0.0.4
Summary: Set of utils to help to work in data and analytics
Author-email: Konstantin Suspitsyn <konstantin.suspitsun@xmail.ru>
Project-URL: Homepage, https://github.com/konstantin-suspitsyn/skautils
Project-URL: Issues, https://github.com/konstantin-suspitsyn/skautils/issues
Classifier: Programming Language :: Python :: 3
Classifier: License :: OSI Approved :: Apache Software License
Classifier: Operating System :: Microsoft :: Windows
Requires-Python: >=3.9
License-File: LICENSE
Requires-Dist: toml >=0.10.2
